pip_author_stats/__init__.py
pip_author_stats/report_generator.py
pip_author_stats-0.0.2.dist-info/LICENSE
pip_author_stats-0.0.2.dist-info/METADATA
pip_author_stats-0.0.2.dist-info/WHEEL
pip_author_stats-0.0.2.dist-info/top_level.txt
pip_author_stats-0.0.2.dist-info/RECORD
