Metadata-Version: 2.1
Name: pip-author-stats
Version: 0.0.2
Summary: A tool to generate statistics report for PyPI authors
Home-page: https://github.com/chigwell/pip_author_stats
Author: Eugene Evstafev
Author-email: chigwel@gmail.com
License: UNKNOWN
Platform: UNKNOWN
Classifier: License :: OSI Approved :: MIT License
Classifier: Development Status :: 3 - Alpha
Classifier: Intended Audience :: Developers
Classifier: Programming Language :: Python :: 3
Classifier: Operating System :: OS Independent
Requires-Python: >=3.6
Requires-Dist: requests
Requires-Dist: pandas
Requires-Dist: matplotlib
Requires-Dist: pypistats
Requires-Dist: bs4
